Workbook

Sheet Balance Sheet
F1: in Crores
A2: Particulars | B2: 2021 | C2: 2022 | D2: 2023 | E2: 2024 | F2: 2025
A3: Assets | B3: 108386 | C3: 117885 | D3: 125816 | E3: 137814 | F3: 148903
A4: Liabilites | B4: 31604 | C4: 42149 | D4: 50021 | E4: 49353 | F4: 52703
A5: Total Equity | B5: 76782 | C5: 75736 | D5: 75795 | E5: 88461 | F5: 96203
A6: Capital Employed | B6: =B5+B4 -> 108386 | C6: =C5+C4 -> 117885 | D6: =D5+D4 -> 125816 | E6: =E5+E4 -> 137814 | F6: =F5+F4 -> 148906

Sheet Profit & Loss
F2: in Crores
A3: Particulars | B3: 2021 | C3: 2022 | D3: 2023 | E3: 2024 | F3: 2025
A4: Revenue | B4: 100472 | C4: 121641 | D4: 146767 | E4: 153670 | F4: 162990
A5: Total Expenses | B5: 75045 | C5: 93826 | D5: 116141 | E5: 122393 | F5: 128982
A6: Operating Profit | B6: 26823 | C6: 30310 | D6: 33606 | E6: 36458 | F6: 38024
A7: Net Profit | B7: 19423 | C7: 22146 | D7: 24108 | E7: 26248 | F7: 26750

Sheet Analysis
A1: Section1:Growth | E1: ROE(Return on Equity) | H1: Section3:Risk
A2: Year- On-Year Growth | D2: 2021 | E2: ='Profit & Loss'!B7/'Balance Sheet'!B5 -> 0.25296293 | H2: Debt to Equity
D3: 2022 | E3: ='Profit & Loss'!C7/'Balance Sheet'!C5 -> 0.29241048 | G3: 2021 | H3: ='Balance Sheet'!B4/'Balance Sheet'!B3 -> 0.29158747
A4: Growth=Current Year−Previous Year​/Previous Year | D4: 2023 | E4: ='Profit & Loss'!D7/'Balance Sheet'!D5 -> 0.31806847 | G4: 2022 | H4: ='Balance Sheet'!C4/'Balance Sheet'!C3 -> 0.35754337
A5: 2021 | B5: =('Profit & Loss'!C4-'Profit & Loss'!B4)/'Profit & Loss'!B4 -> 0.21069552 | D5: 2024 | E5: ='Profit & Loss'!E7/'Balance Sheet'!E5 -> 0.29671833 | G5: 2023 | H5: ='Balance Sheet'!D4/'Balance Sheet'!D3 -> 0.39757265
A6: 2022 | B6: =('Profit & Loss'!C5-'Profit & Loss'!B5)/'Profit & Loss'!B5 -> 0.25026318 | D6: 2025 | E6: ='Profit & Loss'!F7/'Balance Sheet'!F5 -> 0.27805786 | G6: 2024 | H6: ='Balance Sheet'!E4/'Balance Sheet'!E3 -> 0.35811311
A7: 2023 | B7: =('Profit & Loss'!C6-'Profit & Loss'!B6)/'Profit & Loss'!B6 -> 0.13000037 | G7: 2025 | H7: ='Balance Sheet'!F4/'Balance Sheet'!F3 -> 0.35394183
A8: 2024 | B8: =('Profit & Loss'!C7-'Profit & Loss'!B7)/'Profit & Loss'!B7 -> 0.14019461 | E8: ROCE(Return on Capital Employed)
A9: 2025 | D9: 2021 | E9: ='Profit & Loss'!B6/'Balance Sheet'!B6 -> 0.24747661
D10: 2022 | E10: ='Profit & Loss'!C6/'Balance Sheet'!C6 -> 0.25711498
A11: Section2:Profitability | D11: 2023 | E11: ='Profit & Loss'!D6/'Balance Sheet'!D6 -> 0.26710434
D12: 2024 | E12: ='Profit & Loss'!E6/'Balance Sheet'!E6 -> 0.26454497
A13: Operating Margin | B13: ='Profit & Loss'!B6/'Profit & Loss'!B4 -> 0.2669699 | D13: 2025 | E13: ='Profit & Loss'!F6/'Balance Sheet'!F6 -> 0.25535573
B14: ='Profit & Loss'!C6/'Profit & Loss'!C4 -> 0.24917585
A15: Operating Margin=Operating Profit/Revenue | B15: ='Profit & Loss'!D6/'Profit & Loss'!D4 -> 0.22897518
A16: 2021 | B16: ='Profit & Loss'!E6/'Profit & Loss'!E4 -> 0.23724865 | E16: Financial Insights
A17: 2022 | B17: ='Profit & Loss'!F6/'Profit & Loss'!F4 -> 0.23329039
A18: 2023
A19: 2024
A20: 2025
A22: Net Profit Margin
B23: ='Profit & Loss'!B7/'Profit & Loss'!B4 -> 0.19331754
A24: Net Profit Margin=Net Profit/Revenue | B24: ='Profit & Loss'!C7/'Profit & Loss'!C4 -> 0.18206033
B25: ='Profit & Loss'!D7/'Profit & Loss'!D4 -> 0.16426036
A26: 2021 | B26: ='Profit & Loss'!E7/'Profit & Loss'!E4 -> 0.17080757
A27: 2022 | B27: ='Profit & Loss'!F7/'Profit & Loss'!F4 -> 0.1641205
A28: 2023
A29: 2024
A30: 2025

Sheet Valuation
G1: Valuation Insights
A2: Company | B2: EPS | C2: P/E Ratio
A3: Infosys | B3: 16.14 | C3: 18
A4: TCS | B4: 37.92 | C4: 17.8
A5: Wipro | B5: 12.6 | C5: 15.2
G17: Final Conclusion
